Tests/__init__.py
Tests/test_basic.py
konbata/__init__.py
konbata/konbata.py
konbata/Data/Data.py
konbata/Data/__init__.py
konbata/Formats/Format.py
konbata/Formats/__init__.py
konbata/Formats/csv_format.py
konbata/Formats/txt_format.py
konbata/Formats/xlsx_format.py
konbata/Formats/xml_format.py
konbata-0.0.2.dist-info/LICENSE
konbata-0.0.2.dist-info/METADATA
konbata-0.0.2.dist-info/WHEEL
konbata-0.0.2.dist-info/top_level.txt
konbata-0.0.2.dist-info/RECORD
