Metadata-Version: 2.1
Name: konbata
Version: 0.0.2
Summary: Python File Converter for hierarchical data
Home-page: https://github.com/jzeuner/konbata
Author: Jonas Zeuner
Author-email: jzeuner.oss@gmail.com
License: UNKNOWN
Platform: UNKNOWN
Classifier: Programming Language :: Python :: 3
Classifier: License :: OSI Approved :: MIT License
Classifier: Operating System :: OS Independent
Requires-Python: >=3.6
